{
  "keyboard": "knobgoblin",
  "keymap": "default",
  "commit": "046429fa87ab26bd131c262e590aa6cd03dd9f75",
  "layout": "LAYOUT_ortho",
  "layers": [
    [
                 "KC_EQL",  "KC_PSLS", "KC_PAST", "KC_PMNS",
                 "KC_P7",   "KC_P8",   "KC_P9",   "KC_PPLS",
                 "KC_P4",   "KC_P5",   "KC_P6",   "KC_PPLS",
      "KC_MPLY", "KC_P1",   "KC_P2",   "KC_P3",   "KC_PENT",
      "KC_MUTE", "MO(1)",   "KC_P0",   "KC_PDOT", "KC_PENT"
    ],
    [
                 "KC_ESC",  "KC_TRNS", "KC_TRNS", "KC_TRNS",
                 "KC_HOME", "KC_TRNS", "KC_PGUP", "KC_TRNS",
                 "KC_END",  "KC_UP",   "KC_PGDN", "KC_TRNS",
      "KC_TRNS", "KC_LEFT", "KC_DOWN", "KC_RGHT", "KC_SPC",
      "KC_TRNS", "KC_TRNS", "KC_BSPC", "KC_DEL",  "KC_TRNS"
    ]
  ]
}
